mycheats/__init__.py
mycheats/practs.py
mycheats/practicals/Hash Table.py
mycheats/practicals/Queue.py
mycheats/practicals/Retrievehtml.py
mycheats/practicals/__init__.py
mycheats/practicals/arithmeticnumpy.py
mycheats/practicals/armstrong.py
mycheats/practicals/binarysearch.py
mycheats/practicals/bubble_sort.py
mycheats/practicals/deleteelem.py
mycheats/practicals/insertelem.py
mycheats/practicals/insertionsort.py
mycheats/practicals/linearsearch.py
mycheats/practicals/numpyarrayop.py
mycheats/practicals/pattern.py
mycheats/practicals/searchelem.py
mycheats/practicals/selectionsort.py
mycheats/practicals/sgpi.py
mycheats/practicals/singlylinkedlist.py
mycheats/practicals/sortingalgobubble.py
mycheats/practicals/stack.py
py_cheatsheet_ace-0.2.0.dist-info/METADATA
py_cheatsheet_ace-0.2.0.dist-info/WHEEL
py_cheatsheet_ace-0.2.0.dist-info/top_level.txt
py_cheatsheet_ace-0.2.0.dist-info/RECORD
