Metadata-Version: 2.4
Name: py-cheatsheet-ace
Version: 0.2.0
Summary: A personal cheatsheet library for my DS practicals.
Author: prashant shirke
Requires-Python: >=3.6
Dynamic: author
Dynamic: requires-python
Dynamic: summary
